drax_sdk/__init__.py
drax_sdk/broker/__init__.py
drax_sdk/broker/amqp_broker.py
drax_sdk/clients/__init__.py
drax_sdk/clients/drax_core_client.py
drax_sdk/drax.py
drax_sdk/model/__init__.py
drax_sdk/model/automations.py
drax_sdk/model/config.py
drax_sdk/model/dto.py
drax_sdk/model/dynamic.py
drax_sdk/model/event.py
drax_sdk/model/node.py
drax_sdk/model/project.py
drax_sdk/model/utils.py
drax_sdk/utils/__init__.py
drax_sdk/utils/codec.py
drax_sdk/utils/keystore.py
drax_sdk/utils/timestamp.py
drax_sdk-2.3.5.dist-info/METADATA
drax_sdk-2.3.5.dist-info/WHEEL
drax_sdk-2.3.5.dist-info/RECORD
