Metadata-Version: 2.1
Name: drax-sdk
Version: 2.3.5
Summary: Python sdk for Drax IoT Platform
Author: Applica Software Guru
Author-email: info@applica.guru
Requires-Python: >=3.10,<4.0
Classifier: Programming Language :: Python :: 3
Classifier: Programming Language :: Python :: 3.10
Classifier: Programming Language :: Python :: 3.11
Classifier: Programming Language :: Python :: 3.12
Classifier: Programming Language :: Python :: 3.13
Requires-Dist: drax-ecc (>=1.0.7,<2.0.0)
Requires-Dist: pandas (>=2.2.2,<3.0.0)
Requires-Dist: pika (>=1.3.2,<2.0.0)
Requires-Dist: pyarrow (>=16.0.0,<17.0.0)
Requires-Dist: pydantic (>=2.7.0,<3.0.0)
Requires-Dist: python-dotenv (>=1.0.1,<2.0.0)
Requires-Dist: requests (>=2.31.0,<3.0.0)
